docs/__init__.py
docs/md_autogen.py
docs/update_docs.py
keras_text/__init__.py
keras_text/data.py
keras_text/embeddings.py
keras_text/generators.py
keras_text/processing.py
keras_text/sampling.py
keras_text/utils.py
keras_text/models/__init__.py
keras_text/models/layers.py
keras_text/models/sentence_model.py
keras_text/models/sequence_encoders.py
keras_text/models/token_model.py
keras_text-0.1.dist-info/DESCRIPTION.rst
keras_text-0.1.dist-info/METADATA
keras_text-0.1.dist-info/RECORD
keras_text-0.1.dist-info/WHEEL
keras_text-0.1.dist-info/metadata.json
keras_text-0.1.dist-info/top_level.txt
